{"resource":"commonteamroster","parameters":{"TeamID":1610612765,"LeagueID":null,"Season":"1987-88"},"resultSets":[{"name":"CommonTeamRoster","headers":["TeamID","SEASON","LeagueID","PLAYER","NUM","POSITION","HEIGHT","WEIGHT","BIRTH_DATE","AGE","EXP","SCHOOL","PLAYER_ID"],"rowSet":[[1610612765,"1987","00","William Bedford","25","C","7-0","225","DEC 14, 1963",24.0,"1","Memphis",76138],[1610612765,"1987","00","Adrian Dantley","45","F","6-5","208","FEB 26, 1955",33.0,"11","Notre Dame",76504],[1610612765,"1987","00","Darryl Dawkins","50","C","6-11","251","JAN 11, 1957",31.0,"12",null,76539],[1610612765,"1987","00","Joe Dumars","4","G","6-3","190","MAY 24, 1963",25.0,"2","McNeese State",247],[1610612765,"1987","00","James Edwards","53","C","7-1","225","NOV 22, 1955",32.0,"10","Washington",229],[1610612765,"1987","00","Vinnie Johnson","15","G","6-2","200","SEP 01, 1956",31.0,"8","Baylor",77167],[1610612765,"1987","00","Bill Laimbeer","40","C","6-11","245","JAN 01, 1900",88.0,"7","Notre Dame",100263],[1610612765,"1987","00","Ralph Lewis","35","G","6-6","200","MAR 28, 1963",25.0,"R","La Salle",77383],[1610612765,"1987","00","Rick Mahorn","44","F","6-10","240","SEP 21, 1958",29.0,"7","Hampton",328],[1610612765,"1987","00","Chuck Nevitt","42","C","7-5","217","JUN 13, 1959",29.0,"4","North Carolina State",77707],[1610612765,"1987","00","Dennis Rodman","10","F","6-7","210","MAY 13, 1961",27.0,"1","Southeastern Oklahoma State",23],[1610612765,"1987","00","Walker Russell",null,"G","6-5","195","OCT 26, 1960",27.0,"5","Western Michigan",78048],[1610612765,"1987","00","John Salley","22","F","6-11","230","MAY 16, 1964",24.0,"1","Georgia Tech",927],[1610612765,"1987","00","Isiah Thomas","11","G","6-1","180","APR 30, 1961",27.0,"6","Indiana",78318]]},{"name":"Coaches","headers":["TEAM_ID","SEASON","COACH_ID","FIRST_NAME","LAST_NAME","COACH_NAME","COACH_CODE","IS_ASSISTANT","COACH_TYPE","SCHOOL","SORT_SEQUENCE"],"rowSet":[]}]}