{"resource":"playergamelog","parameters":{"PlayerID":78633,"LeagueID":null,"Season":"1984-85","SeasonType":"Regular Season","DateFrom":null,"DateTo":null},"resultSets":[{"name":"PlayerGameLog","headers":["SEASON_ID","Player_ID","Game_ID","GAME_DATE","MATCHUP","WL","MIN","FGM","FGA","FG_PCT","FG3M","FG3A","FG3_PCT","FTM","FTA","FT_PCT","OREB","DREB","REB","AST","STL","BLK","TOV","PF","PTS","PLUS_MINUS","VIDEO_AVAILABLE"],"rowSet":[["21984",78633,"0028400073","NOV 08, 1984","SEA @ HOU","L",9,2,6,0.333,0,1,0.000,0,0,null,0,0,0,1,2,0,0,0,4,null,0],["21984",78633,"0028400023","OCT 30, 1984","SEA @ POR","L",15,0,4,0.000,0,0,null,0,0,null,0,3,3,1,1,0,2,0,0,null,0],["21984",78633,"0028400001","OCT 26, 1984","SEA vs. UTH","W",2,0,0,null,0,0,null,0,0,null,0,0,0,0,0,0,0,2,0,null,0]]}]}