{"resource":"commonteamroster","parameters":{"TeamID":1610612764,"LeagueID":null,"Season":"1990-91"},"resultSets":[{"name":"CommonTeamRoster","headers":["TeamID","SEASON","LeagueID","PLAYER","NUM","POSITION","HEIGHT","WEIGHT","BIRTH_DATE","AGE","EXP","SCHOOL","PLAYER_ID"],"rowSet":[[1610612764,"1990","00","Mark Alarie","31","F","6-8","217","DEC 11, 1963",27.0,"4","Duke",76019],[1610612764,"1990","00","Ledell Eackles","21","G","6-5","220","NOV 24, 1966",24.0,"2","New Orleans",289],[1610612764,"1990","00","Pervis Ellison","43","C","6-9","210","APR 03, 1967",24.0,"1","Louisville",442],[1610612764,"1990","00","A.J. English","14","G","6-3","175","JUL 11, 1967",23.0,"R","Virginia Union",76672],[1610612764,"1990","00","Greg Foster","42","C","6-11","240","OCT 03, 1968",22.0,"R","Texas-El Paso",323],[1610612764,"1990","00","Harvey Grant","44","F","6-8","195","JUL 04, 1965",25.0,"2","Oklahoma",265],[1610612764,"1990","00","Tom Hammonds","12","F","6-9","215","MAR 27, 1967",24.0,"1","Georgia Tech",67],[1610612764,"1990","00","Byron Irvin","32","G","6-5","190","DEC 02, 1966",24.0,"1","Missouri",77096],[1610612764,"1990","00","Charles Jones","23","C","6-9","215","APR 03, 1957",34.0,"7","Albany State (GA)",279],[1610612764,"1990","00","Bernard King","30","F","6-7","205","DEC 04, 1956",34.0,"12","Tennessee",77264],[1610612764,"1990","00","Larry Robinson","2","G","6-3","180","JAN 11, 1968",23.0,"R","Centenary (LA)",1683],[1610612764,"1990","00","Clinton Smith","22","F","6-6","210","JAN 19, 1964",27.0,"1","Cleveland State",78181],[1610612764,"1990","00","Darrell Walker","5","G","6-4","180","MAR 09, 1961",30.0,"7","Arkansas",78437],[1610612764,"1990","00","John Williams","34","F","6-8","235","OCT 26, 1966",24.0,"4","Louisiana State",78554],[1610612764,"1990","00","Haywoode Workman","3","G","6-2","180","JAN 23, 1966",25.0,"1","Oral Roberts",906]]},{"name":"Coaches","headers":["TEAM_ID","SEASON","COACH_ID","FIRST_NAME","LAST_NAME","COACH_NAME","COACH_CODE","IS_ASSISTANT","COACH_TYPE","SCHOOL","SORT_SEQUENCE"],"rowSet":[]}]}