{"resource":"commonteamroster","parameters":{"TeamID":1610612750,"LeagueID":null,"Season":"2009-10"},"resultSets":[{"name":"CommonTeamRoster","headers":["TeamID","SEASON","LeagueID","PLAYER","NUM","POSITION","HEIGHT","WEIGHT","BIRTH_DATE","AGE","EXP","SCHOOL","PLAYER_ID"],"rowSet":[[1610612750,"2009","00","Ryan Hollins","1","C","7-0","230","OCT 10, 1984",25.0,"3","UCLA",200797],[1610612750,"2009","00","Damien Wilkins","3","F-G","6-6","225","JAN 11, 1980",30.0,"5","Georgia",2863],[1610612750,"2009","00","Oleksiy Pecherov","4","F-C","7-0","234","DEC 08, 1985",24.0,"2","Donetsk, Ukraine",200762],[1610612750,"2009","00","Ramon Sessions","7","G","6-3","190","APR 11, 1986",24.0,"2","Nevada",201196],[1610612750,"2009","00","Ryan Gomes","8","F","6-7","245","SEP 01, 1982",27.0,"4","Providence",101155],[1610612750,"2009","00","Jonny Flynn","10","G","6-0","185","FEB 06, 1989",21.0,"R","Syracuse",201938],[1610612750,"2009","00","Sasha Pavlovic","11","G-F","6-7","235","NOV 15, 1983",26.0,"6","Bar, Montenegro",2562],[1610612750,"2009","00","Brian Cardinal","14","F","6-8","240","MAY 02, 1977",33.0,"9","Purdue",2073],[1610612750,"2009","00","Nathan Jawai","15","F","6-10","280","OCT 10, 1986",23.0,"1","Midland",201605],[1610612750,"2009","00","Wayne Ellington","19","G","6-4","200","NOV 29, 1987",22.0,"R","North Carolina",201961],[1610612750,"2009","00","Corey Brewer","22","G-F","6-9","188","MAR 05, 1986",24.0,"2","Florida",201147],[1610612750,"2009","00","Al Jefferson","25","C-F","6-10","265","JAN 04, 1985",25.0,"5","Prentiss HS (MS)",2744],[1610612750,"2009","00","Darko Milicic","31","C","7-0","275","JUN 20, 1985",25.0,"6","Novi Sad, Serbia",2545],[1610612750,"2009","00","Greg Stiemsma","34","C","6-11","260","SEP 26, 1985",24.0,"R","Wisconsin",201880],[1610612750,"2009","00","Kevin Love","42","F-C","6-10","260","SEP 07, 1988",21.0,"1","UCLA",201567]]},{"name":"Coaches","headers":["TEAM_ID","SEASON","COACH_ID","FIRST_NAME","LAST_NAME","COACH_NAME","COACH_CODE","IS_ASSISTANT","COACH_TYPE","SCHOOL","SORT_SEQUENCE"],"rowSet":[[1610612750,"2009","RAM165741","Kurt","Rambis","Kurt Rambis","kurt_rambis",1.0,"Head Coach","College - Santa Clara",null],[1610612750,"2009","WOH407041","Dave","Wohl","Dave Wohl","dave_wohl",2.0,"Assistant Coach","College - Pennsylvania",134.0],[1610612750,"2009","THE414916","Reggie","Theus","Reggie Theus","reggie_theus",2.0,"Assistant Coach","College - UNLV",135.0],[1610612750,"2009","LAI414916","Bill","Laimbeer","Bill Laimbeer","bill_laimbeer",2.0,"Assistant Coach","College - Notre Dame",136.0],[1610612750,"2009","BIC363464","J.B.","Bickerstaff","J.B. Bickerstaff","jb_bickerstaff",2.0,"Assistant Coach","College - Minnesota",137.0],[1610612750,"2009","FAR531079","Gregg","Farnam","Gregg Farnam","gregg_farnam",3.0,"Trainer","College - St. Cloud State",140.0],[1610612750,"2009","VIT173362","Dave","Vitel","Dave Vitel","dave_vitel",5.0,"Strength and Conditioning Coach","College - Wisconsin-Whitewater",139.0],[1610612750,"2009","HAS158616","Brent","Haskins","Brent Haskins","brent_haskins",16.0,"Assistant Coach","College - Minnesota",138.0]]}]}