{"resource":"commonteamroster","parameters":{"TeamID":1610612755,"LeagueID":null,"Season":"1986-87"},"resultSets":[{"name":"CommonTeamRoster","headers":["TeamID","SEASON","LeagueID","PLAYER","NUM","POSITION","HEIGHT","WEIGHT","BIRTH_DATE","AGE","EXP","SCHOOL","PLAYER_ID"],"rowSet":[[1610612755,"1986","00","Charles Barkley","34","F","6-6","252","FEB 20, 1963",24.0,"2","Auburn",787],[1610612755,"1986","00","Maurice Cheeks","10","G","6-1","180","SEP 08, 1956",30.0,"8","West Texas A&M",76385],[1610612755,"1986","00","Steve Colter","14","G","6-3","165","JUL 24, 1962",24.0,"2","New Mexico State",306],[1610612755,"1986","00","Julius Erving","6","F","6-7","200","FEB 22, 1950",37.0,"10","Massachusetts",76681],[1610612755,"1986","00","World Free","12","G","6-3","185","DEC 09, 1953",33.0,"11","Guilford",76753],[1610612755,"1986","00","Kenny Green","21","G","6-6","210","OCT 11, 1964",22.0,"1","Wake Forest",76869],[1610612755,"1986","00","Roy Hinson","23","C","6-9","210","MAY 02, 1961",26.0,"3","Rutgers",77030],[1610612755,"1986","00","Jim Lampley","11","F","6-10","230","JUL 02, 1960",26.0,"R","Arkansas-Little Rock",77333],[1610612755,"1986","00","Tim McCormick","40","C","6-11","240","MAR 10, 1962",25.0,"2","Michigan",77516],[1610612755,"1986","00","Mark McNamara","31","C","6-11","235","JUN 08, 1959",28.0,"3","California",77558],[1610612755,"1986","00","Cliff T. Robinson","4","F","6-9","220","MAR 13, 1960",27.0,"7","Southern California",77986],[1610612755,"1986","00","Jeff Ruland","43","C","6-10","240","DEC 16, 1958",28.0,"5","Iona",78041],[1610612755,"1986","00","Andrew Toney","22","G","6-3","178","NOV 23, 1957",29.0,"6","Louisiana-Lafayette",78351],[1610612755,"1986","00","Danny Vranes","20","F","6-7","210","OCT 29, 1958",28.0,"5","Utah",78423],[1610612755,"1986","00","David Wingate","25","G","6-5","185","DEC 15, 1963",23.0,"R","Georgetown",766]]},{"name":"Coaches","headers":["TEAM_ID","SEASON","COACH_ID","FIRST_NAME","LAST_NAME","COACH_NAME","COACH_CODE","IS_ASSISTANT","COACH_TYPE","SCHOOL","SORT_SEQUENCE"],"rowSet":[]}]}