{"resource":"commonteamroster","parameters":{"TeamID":1610612740,"LeagueID":null,"Season":"2004-05"},"resultSets":[{"name":"CommonTeamRoster","headers":["TeamID","SEASON","LeagueID","PLAYER","NUM","POSITION","HEIGHT","WEIGHT","BIRTH_DATE","AGE","EXP","SCHOOL","PLAYER_ID"],"rowSet":[[1610612740,"2004","00","Dan Dickau","2","G","6-0","190","SEP 16, 1978",26.0,"2","Gonzaga",2424],[1610612740,"2004","00","Jackson Vroman","4","F-C","6-10","220","JUN 06, 1981",24.0,"R","Iowa State",2761],[1610612740,"2004","00","George Lynch","9","F","6-8","235","SEP 03, 1970",34.0,"11","North Carolina",248],[1610612740,"2004","00","Bostjan Nachbar","10","F","6-9","221","JUL 03, 1980",24.0,"2","Italy",2411],[1610612740,"2004","00","Chris Andersen","12","F-C","6-10","228","JUL 07, 1978",26.0,"3","Blinn",2365],[1610612740,"2004","00","Maciej Lampe","15","F","6-11","275","FEB 05, 1985",20.0,"1","Poland",2573],[1610612740,"2004","00","Jamaal Magloire","21","C","6-11","259","MAY 21, 1978",27.0,"4","Kentucky",2048],[1610612740,"2004","00","JR Smith","23","G","6-6","220","SEP 09, 1985",19.0,"R","St. Benedict's Prep (NJ)",2747],[1610612740,"2004","00","David West","30","F","6-8","226","AUG 29, 1980",24.0,"1","Xavier",2561],[1610612740,"2004","00","Casey Jacobsen","32","G-F","6-6","215","MAR 19, 1981",24.0,"2","Stanford",2418],[1610612740,"2004","00","Lee Nailon","33","F","6-9","238","FEB 22, 1975",30.0,"4","Texas Christian",1924],[1610612740,"2004","00","P.J. Brown","42","C-F","6-11","239","OCT 14, 1969",35.0,"11","Louisiana Tech",136]]},{"name":"Coaches","headers":["TEAM_ID","SEASON","COACH_ID","FIRST_NAME","LAST_NAME","COACH_NAME","COACH_CODE","IS_ASSISTANT","COACH_TYPE","SCHOOL","SORT_SEQUENCE"],"rowSet":[[1610612740,"2004","SCO311091","Byron","Scott","Byron Scott","byron_scott",1.0,"Head Coach","College - Arizona State",null],[1610612740,"2004","WAL248799","Darrell","Walker","Darrell Walker","darrell_walker",2.0,"Assistant Coach","College - Arkansas",42.0],[1610612740,"2004","CLE276486","Jim","Cleamons","Jim Cleamons","jim_cleamons",2.0,"Assistant Coach","College - Ohio State",43.0],[1610612740,"2004","GAT553347","Kenny","Gattison","Kenny Gattison","kenny_gattison",2.0,"Assistant Coach","College - Old Dominion",44.0],[1610612740,"2004","KOF337423","Terry","Kofler","Terry Kofler","terry_kofler",3.0,"Trainer","College - Xavier",45.0],[1610612740,"2004","MAN711700","Jack","Manson","Jack Manson","jack_manson",5.0,"Strength and Conditioning Coach","College - Howard",46.0]]}]}