{"resource":"commonteamroster","parameters":{"TeamID":1610612751,"LeagueID":null,"Season":"2010-11"},"resultSets":[{"name":"CommonTeamRoster","headers":["TeamID","SEASON","LeagueID","PLAYER","NUM","POSITION","HEIGHT","WEIGHT","BIRTH_DATE","AGE","EXP","SCHOOL","PLAYER_ID"],"rowSet":[[1610612751,"2010","00","Sundiata Gaines","0","G","6-1","200","APR 18, 1986",25.0,"1","Georgia",202178],[1610612751,"2010","00","Jordan Farmar","2","G","6-2","180","NOV 30, 1986",24.0,"4","UCLA",200770],[1610612751,"2010","00","Mario West","6","G","6-5","210","JUN 19, 1984",27.0,"3","Georgia Tech",201238],[1610612751,"2010","00","Deron Williams","8","G","6-3","209","JUN 26, 1984",27.0,"5","Illinois",101114],[1610612751,"2010","00","Damion James","10","F","6-7","220","OCT 07, 1987",23.0,"R","Texas",202345],[1610612751,"2010","00","Brook Lopez","11","C","7-0","265","APR 01, 1988",23.0,"2","Stanford",201572],[1610612751,"2010","00","Ben Uzoh","18","G","6-3","205","MAR 18, 1988",23.0,"R","Tulsa",202386],[1610612751,"2010","00","Sasha Vujacic","20","G","6-7","205","MAR 08, 1984",27.0,"6","Maribor, Slovenia",2756],[1610612751,"2010","00","Travis Outlaw","21","F","6-9","207","SEP 18, 1984",26.0,"7","Starkville HS (MS)",2566],[1610612751,"2010","00","Anthony Morrow","22","G","6-5","210","SEP 27, 1985",25.0,"2","Georgia Tech",201627],[1610612751,"2010","00","Stephen Graham","26","G-F","6-6","215","JUN 11, 1982",29.0,"5","Oklahoma State",101211],[1610612751,"2010","00","Johan Petro","27","C","7-0","247","JAN 27, 1986",25.0,"5","Paris, France",101130],[1610612751,"2010","00","Brandan Wright","34","F","6-10","210","OCT 05, 1987",23.0,"2","North Carolina",201148],[1610612751,"2010","00","Kris Humphries","43","F","6-9","235","FEB 06, 1985",26.0,"6","Minnesota",2743],[1610612751,"2010","00","Dan Gadzuric","50","C","6-11","240","FEB 02, 1978",33.0,"8","UCLA",2429]]},{"name":"Coaches","headers":["TEAM_ID","SEASON","COACH_ID","FIRST_NAME","LAST_NAME","COACH_NAME","COACH_CODE","IS_ASSISTANT","COACH_TYPE","SCHOOL","SORT_SEQUENCE"],"rowSet":[[1610612751,"2010","MIT497973","Sam","Mitchell","Sam Mitchell","sam_mitchell",2.0,"Assistant Coach","College - Mercer",144.0],[1610612751,"2010","LOY177980","John","Loyer","John Loyer","john_loyer",2.0,"Assistant Coach","College - Akron",145.0],[1610612751,"2010","JON549410","Popeye","Jones","Popeye Jones","popeye_jones",2.0,"Assistant Coach","College - Murray State",146.0],[1610612751,"2010","BAR665851","Tom","Barrise","Tom Barrise","tom_barrise",2.0,"Assistant Coach","College - Fairleigh Dickinson",147.0],[1610612751,"2010","WAL642574","Tim","Walsh","Tim Walsh","tim_walsh",3.0,"Trainer","College - Upsala",148.0],[1610612751,"2010","DAL056390","Rich","Dalatri","Rich Dalatri","rich_dalatri",11.0,"Assistant Coach Strength and Conditioning Coach","College - Louisiana Tech",149.0]]}]}