{"resource":"commonteamroster","parameters":{"TeamID":1610612738,"LeagueID":null,"Season":"1985-86"},"resultSets":[{"name":"CommonTeamRoster","headers":["TeamID","SEASON","LeagueID","PLAYER","NUM","POSITION","HEIGHT","WEIGHT","BIRTH_DATE","AGE","EXP","SCHOOL","PLAYER_ID"],"rowSet":[[1610612738,"1985","00","Danny Ainge","44","G","6-5","175","MAR 17, 1959",27.0,"4","Brigham Young",76017],[1610612738,"1985","00","Larry Bird","33","F","6-9","220","DEC 07, 1956",29.0,"6","Indiana State",1449],[1610612738,"1985","00","Rick Carlisle","34","G","6-5","210","OCT 27, 1959",26.0,"1","Virginia",76342],[1610612738,"1985","00","Dennis Johnson","3","G","6-4","185","SEP 18, 1954",31.0,"9","Pepperdine",77141],[1610612738,"1985","00","Greg Kite","50","C","6-11","250","AUG 05, 1961",24.0,"2","Brigham Young",1123],[1610612738,"1985","00","Kevin McHale","32","F","6-10","210","DEC 19, 1957",28.0,"5","Minnesota",1450],[1610612738,"1985","00","Robert Parish","0","C","7-1","230","AUG 30, 1953",32.0,"9","Centenary (LA)",305],[1610612738,"1985","00","Jerry Sichting","12","G","6-1","168","NOV 29, 1956",29.0,"5","Purdue",78146],[1610612738,"1985","00","David Thirdkill","45","F","6-7","195","APR 12, 1960",26.0,"3","Bradley",78314],[1610612738,"1985","00","Sam Vincent","11","G","6-2","185","MAY 18, 1963",23.0,"R","Michigan State",78417],[1610612738,"1985","00","Bill Walton","5","C","6-11","210","NOV 05, 1952",33.0,"8","UCLA",78450],[1610612738,"1985","00","Scott Wedman","8","F","6-7","215","JUL 29, 1952",33.0,"11","Colorado",78482],[1610612738,"1985","00","Sly Williams","35","F","6-7","210","JAN 26, 1958",28.0,"6","Rhode Island",78570]]},{"name":"Coaches","headers":["TEAM_ID","SEASON","COACH_ID","FIRST_NAME","LAST_NAME","COACH_NAME","COACH_CODE","IS_ASSISTANT","COACH_TYPE","SCHOOL","SORT_SEQUENCE"],"rowSet":[]}]}