{"resource":"commonteamroster","parameters":{"TeamID":1610612744,"LeagueID":null,"Season":"1987-88"},"resultSets":[{"name":"CommonTeamRoster","headers":["TeamID","SEASON","LeagueID","PLAYER","NUM","POSITION","HEIGHT","WEIGHT","BIRTH_DATE","AGE","EXP","SCHOOL","PLAYER_ID"],"rowSet":[[1610612744,"1987","00","Dave Feitl","5","C","6-11","235","JUN 08, 1962",26.0,"1","Texas-El Paso",76703],[1610612744,"1987","00","Tellis Frank","32","F","6-10","225","APR 26, 1965",23.0,"R","Western Kentucky",76748],[1610612744,"1987","00","Winston Garland","12","G","6-2","170","DEC 19, 1964",23.0,"R","Missouri State",76782],[1610612744,"1987","00","Steve Harris","11","G","6-5","195","OCT 15, 1963",24.0,"2","Tulsa",76960],[1610612744,"1987","00","Rod Higgins","22","F","6-7","200","JAN 31, 1960",28.0,"5","Fresno State",77019],[1610612744,"1987","00","Dave Hoppen","52","C","6-11","235","MAR 13, 1964",24.0,"R","Nebraska",77053],[1610612744,"1987","00","Ben McDonald","30","F","6-8","210","JUL 20, 1962",25.0,"2","California-Irvine",77524],[1610612744,"1987","00","Chris Mullin","17","F","6-6","200","JUL 30, 1963",24.0,"2","St. John's (NY)",904],[1610612744,"1987","00","Ralph Sampson","50","C","7-4","228","JUL 07, 1960",27.0,"4","Virginia",78055],[1610612744,"1987","00","Larry Smith","13","F","6-8","215","JAN 18, 1958",30.0,"7","Alcorn State",78195],[1610612744,"1987","00","Otis Smith","18","F","6-5","210","JAN 30, 1964",24.0,"1","Jacksonville",78198],[1610612744,"1987","00","Terry Teagle","20","G","6-5","195","APR 10, 1960",28.0,"5","Baylor",78304],[1610612744,"1987","00","Mark Wade","4","G","5-11","160","OCT 15, 1965",22.0,"R","Nevada-Las Vegas",78426],[1610612744,"1987","00","Kermit Washington","3","F","6-8","230","SEP 17, 1951",36.0,"9","American",78467],[1610612744,"1987","00","Tony White","4","G","6-2","170","FEB 15, 1965",23.0,"R","Tennessee",78514],[1610612744,"1987","00","Jerome Whitehead","33","C","6-10","220","SEP 30, 1956",31.0,"9","Marquette",78516]]},{"name":"Coaches","headers":["TEAM_ID","SEASON","COACH_ID","FIRST_NAME","LAST_NAME","COACH_NAME","COACH_CODE","IS_ASSISTANT","COACH_TYPE","SCHOOL","SORT_SEQUENCE"],"rowSet":[[1610612744,"1987","KAR407791","George","Karl","George Karl","george_karl",1.0,"Head Coach","College - North Carolina",null]]}]}