{"resource":"commonteamroster","parameters":{"TeamID":1610612765,"LeagueID":null,"Season":"1990-91"},"resultSets":[{"name":"CommonTeamRoster","headers":["TeamID","SEASON","LeagueID","PLAYER","NUM","POSITION","HEIGHT","WEIGHT","BIRTH_DATE","AGE","EXP","SCHOOL","PLAYER_ID"],"rowSet":[[1610612765,"1990","00","Mark Aguirre","23","F","6-6","232","DEC 10, 1959",31.0,"9","DePaul",76016],[1610612765,"1990","00","William Bedford","00","C","7-0","225","DEC 14, 1963",27.0,"3","Memphis",76138],[1610612765,"1990","00","Lance Blanks","32","G","6-4","190","SEP 09, 1966",24.0,"R","Texas",76183],[1610612765,"1990","00","Joe Dumars","4","G","6-3","190","MAY 24, 1963",28.0,"5","McNeese State",247],[1610612765,"1990","00","James Edwards","53","C","7-1","225","NOV 22, 1955",35.0,"13","Washington",229],[1610612765,"1990","00","Scott Hastings","35","F","6-10","235","JUN 03, 1960",31.0,"8","Arkansas",76968],[1610612765,"1990","00","Gerald Henderson","12","G","6-2","175","JAN 16, 1956",35.0,"11","Virginia Commonwealth",76993],[1610612765,"1990","00","Vinnie Johnson","15","G","6-2","200","SEP 01, 1956",34.0,"11","Baylor",77167],[1610612765,"1990","00","Bill Laimbeer","40","C","6-11","245","JAN 01, 1900",91.0,"10","Notre Dame",100263],[1610612765,"1990","00","John Long","25","G","6-5","195","AUG 28, 1956",34.0,"12","Detroit Mercy",1381],[1610612765,"1990","00","Dennis Rodman","10","F","6-7","210","MAY 13, 1961",30.0,"4","Southeastern Oklahoma State",23],[1610612765,"1990","00","Tree Rollins","30","C","7-1","235","JUN 16, 1955",36.0,"13","Clemson",78014],[1610612765,"1990","00","John Salley","22","F","6-11","230","MAY 16, 1964",27.0,"4","Georgia Tech",927],[1610612765,"1990","00","Isiah Thomas","11","G","6-1","180","APR 30, 1961",30.0,"9","Indiana",78318]]},{"name":"Coaches","headers":["TEAM_ID","SEASON","COACH_ID","FIRST_NAME","LAST_NAME","COACH_NAME","COACH_CODE","IS_ASSISTANT","COACH_TYPE","SCHOOL","SORT_SEQUENCE"],"rowSet":[]}]}