{"resource":"commonteamroster","parameters":{"TeamID":1610612739,"LeagueID":null,"Season":"2016-17"},"resultSets":[{"name":"CommonTeamRoster","headers":["TeamID","SEASON","LeagueID","PLAYER","NUM","POSITION","HEIGHT","WEIGHT","BIRTH_DATE","AGE","EXP","SCHOOL","PLAYER_ID"],"rowSet":[[1610612739,"2016","00","Kevin Love","0","F","6-10","251","SEP 07, 1988",28.0,"8","UCLA",201567],[1610612739,"2016","00","James Jones","1","G-F","6-8","218","OCT 04, 1980",36.0,"13","Miami (FL)",2592],[1610612739,"2016","00","Kyrie Irving","2","G","6-3","193","MAR 23, 1992",25.0,"5","Duke",202681],[1610612739,"2016","00","Derrick Williams","3","F","6-8","240","MAY 25, 1991",26.0,"5","Arizona",202682],[1610612739,"2016","00","Iman Shumpert","4","G","6-5","220","JUN 26, 1990",27.0,"5","Georgia Tech",202697],[1610612739,"2016","00","JR Smith","5","G","6-6","225","SEP 09, 1985",31.0,"12","St. Benedict's Prep (NJ)",2747],[1610612739,"2016","00","Channing Frye","8","F","6-11","255","MAY 17, 1983",34.0,"10","Arizona",101112],[1610612739,"2016","00","Tristan Thompson","13","C","6-9","238","MAR 13, 1991",26.0,"5","Texas",202684],[1610612739,"2016","00","Kay Felder","20","G","5-9","176","MAR 29, 1995",22.0,"R","Oakland",1627770],[1610612739,"2016","00","LeBron James","23","F","6-8","250","DEC 30, 1984",32.0,"13","St. Vincent-St. Mary HS (OH)",2544],[1610612739,"2016","00","Richard Jefferson","24","F","6-7","233","JUN 21, 1980",37.0,"15","Arizona",2210],[1610612739,"2016","00","Kyle Korver","26","G","6-7","212","MAR 17, 1981",36.0,"13","Creighton",2594],[1610612739,"2016","00","Dahntay Jones","30","G-F","6-6","225","DEC 27, 1980",36.0,"12","Duke",2563],[1610612739,"2016","00","Deron Williams","31","G","6-3","200","JUN 26, 1984",33.0,"11","Illinois",101114],[1610612739,"2016","00","Edy Tavares","40","C","7-3","265","MAR 22, 1992",25.0,"1",null,204002]]},{"name":"Coaches","headers":["TEAM_ID","SEASON","COACH_ID","FIRST_NAME","LAST_NAME","COACH_NAME","COACH_CODE","IS_ASSISTANT","COACH_TYPE","SCHOOL","SORT_SEQUENCE"],"rowSet":[[1610612739,"2016","LUE029287","Tyronn","Lue","Tyronn Lue","tyronn_lue",1.0,"Head Coach","College - Nebraska",null],[1610612739,"2016","BOY575488","Jim","Boylan","Jim Boylan","jim_boylan",2.0,"Assistant Coach","College - Marquette",71.0],[1610612739,"2016","DRE490098","Larry","Drew","Larry Drew","larry_drew",2.0,"Assistant Coach","College - Missouri",72.0],[1610612739,"2016","POS200481","James","Posey","James Posey","james_posey",2.0,"Assistant Coach","College - Xavier (Ohio)",73.0],[1610612739,"2016","HAN034231","Phil","Handy","Phil Handy","phil_handy",2.0,"Assistant Coach","College - Hawaii",74.0],[1610612739,"2016","LON629966","Mike","Longabardi","Mike Longabardi","mike_longabardi",2.0,"Assistant Coach","College - Frostburg State",75.0],[1610612739,"2016","SPI525400","Steve","Spiro","Steve Spiro","steve_spiro",3.0,"Trainer","College - Temple",76.0],[1610612739,"2016","MIL371131","Derek","Millender","Derek Millender","derek_millender",5.0,"Strength and Conditioning Coach","College - South Alabama",77.0]]}]}