{"resource":"playergamelog","parameters":{"PlayerID":977,"LeagueID":null,"Season":"2013-14","SeasonType":"Regular Season","DateFrom":null,"DateTo":null},"resultSets":[{"name":"PlayerGameLog","headers":["SEASON_ID","Player_ID","Game_ID","GAME_DATE","MATCHUP","WL","MIN","FGM","FGA","FG_PCT","FG3M","FG3A","FG3_PCT","FTM","FTA","FT_PCT","OREB","DREB","REB","AST","STL","BLK","TOV","PF","PTS","PLUS_MINUS","VIDEO_AVAILABLE"],"rowSet":[["22013",977,"0021300366","DEC 17, 2013","LAL @ MEM","W",33,9,18,0.500,1,1,1.000,2,2,1.000,1,4,5,4,1,1,4,1,21,2,1],["22013",977,"0021300357","DEC 16, 2013","LAL @ ATL","L",32,4,14,0.286,0,5,0.000,0,1,0.000,0,3,3,6,2,0,5,1,8,-4,1],["22013",977,"0021300342","DEC 14, 2013","LAL @ CHA","W",32,8,15,0.533,2,5,0.400,3,3,1.000,0,7,7,8,0,0,7,1,21,5,1],["22013",977,"0021300336","DEC 13, 2013","LAL @ OKC","L",23,2,6,0.333,0,0,0.000,0,0,0.000,0,1,1,13,2,0,7,1,4,-16,1],["22013",977,"0021300317","DEC 10, 2013","LAL vs. PHX","L",29,6,11,0.545,0,2,0.000,8,8,1.000,0,2,2,3,0,0,3,2,20,-3,1],["22013",977,"0021300303","DEC 08, 2013","LAL vs. TOR","L",28,2,9,0.222,0,3,0.000,5,7,0.714,1,7,8,4,2,0,8,3,9,-16,1]]}]}