{"resource":"commonteamroster","parameters":{"TeamID":1610612764,"LeagueID":null,"Season":"2009-10"},"resultSets":[{"name":"CommonTeamRoster","headers":["TeamID","SEASON","LeagueID","PLAYER","NUM","POSITION","HEIGHT","WEIGHT","BIRTH_DATE","AGE","EXP","SCHOOL","PLAYER_ID"],"rowSet":[[1610612764,"2009","00","Gilbert Arenas","0","G","6-4","215","JAN 06, 1982",28.0,"8","Arizona",2240],[1610612764,"2009","00","Nick Young","1","G","6-6","200","JUN 01, 1985",25.0,"2","Southern California",201156],[1610612764,"2009","00","Shaun Livingston","2","G","6-7","185","SEP 11, 1985",24.0,"4","Peoria Central HS (IL)",2733],[1610612764,"2009","00","Quinton Ross","3","G-F","6-6","193","APR 30, 1981",29.0,"5","Southern Methodist",2624],[1610612764,"2009","00","Josh Howard","5","G-F","6-7","210","APR 28, 1980",30.0,"6","Wake Forest",2572],[1610612764,"2009","00","Mike Miller","6","G-F","6-8","218","FEB 19, 1980",30.0,"9","Florida",2034],[1610612764,"2009","00","Andray Blatche","7","F-C","6-11","248","AUG 22, 1986",23.0,"4","South Kent Prep (CT)",101154],[1610612764,"2009","00","Javaris Crittenton","8","G","6-5","200","DEC 31, 1987",22.0,"2","Georgia Tech",201159],[1610612764,"2009","00","Cedric Jackson","9","G","6-3","190","MAR 05, 1986",24.0,"R","Cleveland State",202132],[1610612764,"2009","00","Earl Boykins","12","G","5-5","133","JUN 02, 1976",34.0,"10","Eastern Michigan",1863],[1610612764,"2009","00","Al Thornton","14","F","6-8","220","DEC 07, 1983",26.0,"2","Florida State",201154],[1610612764,"2009","00","Randy Foye","15","G","6-4","213","SEP 24, 1983",26.0,"3","Villanova",200751],[1610612764,"2009","00","Cartier Martin","20","G-F","6-7","220","NOV 20, 1984",25.0,"1","Kansas State",201858],[1610612764,"2009","00","Fabricio Oberto","21","F-C","6-10","245","MAR 21, 1975",35.0,"4","Las Varillas, Argentina",101177],[1610612764,"2009","00","James Singleton","22","F","6-8","230","JUL 20, 1981",28.0,"5","Murray State",101189],[1610612764,"2009","00","JaVale McGee","34","C","7-0","252","JAN 19, 1988",22.0,"1","Nevada",201580]]},{"name":"Coaches","headers":["TEAM_ID","SEASON","COACH_ID","FIRST_NAME","LAST_NAME","COACH_NAME","COACH_CODE","IS_ASSISTANT","COACH_TYPE","SCHOOL","SORT_SEQUENCE"],"rowSet":[[1610612764,"2009","WIT414915","Randy","Wittman","Randy Wittman","randy_wittman",2.0,"Assistant Coach","College - Indiana",220.0],[1610612764,"2009","ZIE563609","Don","Zierden","Don Zierden","don_zierden",2.0,"Assistant Coach","College - Mount Senario",221.0],[1610612764,"2009","CAS660716","Sam","Cassell","Sam Cassell","sam_cassell",2.0,"Assistant Coach","College - Florida State",222.0],[1610612764,"2009","UNS410041","Wes","Unseld Jr.","Wes Unseld Jr.","wes_unseld_jr",2.0,"Assistant Coach","College - Johns Hopkins",223.0],[1610612764,"2009","SAU634747","Ryan","Saunders","Ryan Saunders","ryan_saunders",2.0,"Assistant Coach","College - Minnesota",224.0],[1610612764,"2009","WEL202845","Mike","Wells","Mike Wells","mike_wells",2.0,"Assistant Coach","College - Mt. Vernon Nazarene",225.0],[1610612764,"2009","BAN165741","Gene","Banks","Gene Banks","gene_banks",2.0,"Assistant Coach","College - Duke",226.0],[1610612764,"2009","WAT052542","Eric","Waters","Eric Waters","eric_waters",3.0,"Trainer","College - Iowa",227.0],[1610612764,"2009","CLE297111","Drew","Cleary","Drew Cleary","drew_cleary",5.0,"Strength and Conditioning Coach","College - Lewis-Clark (ID)",228.0]]}]}